Workbook

Sheet Dashboard
B2: RETAIL SALES PERFORMANCE
B4: Executive dashboard | Revenue, volume, customer experience and sales-team performance
B6: FILTERS
B7: Date From | D7: Date To | F7: Product | H7: Category | J7: Region | L7: Salesperson
B8: 46025 | D8: 46111 | F8: All | H8: All | J8: All | L8: All
B10: TOTAL REVENUE | E10: TOTAL ORDERS | H10: TOTAL QUANTITY | K10: AVERAGE ORDER VALUE
B11: ='Dashboard Calc'!B2 -> 12258000 | E11: ='Dashboard Calc'!B3 -> 30 | H11: ='Dashboard Calc'!B4 -> 149 | K11: ='Dashboard Calc'!B5 -> 408600
B14: Avg. Customer Rating | E14: Top Product | H14: Top Region | K14: Top Salesperson
B15: ='Dashboard Calc'!B6 -> 4.3 | E15: ='Dashboard Calc'!B7 -> Phone | H15: ='Dashboard Calc'!B8 -> South | K15: ='Dashboard Calc'!B9 -> Tunde
B17: SALES TREND | H17: PRODUCT MIX
B33: CATEGORY PERFORMANCE | H33: REGIONAL PERFORMANCE
B48: SALES TEAM | H48: CUSTOMER EXPERIENCE
B65: Data note: Revenue = Quantity × Unit Price. The dataset contains no cost/expense fields, so profit and margin metrics are intentionally excluded.

Sheet Retail Sales Data
A1: Order_ID | B1: Date | C1: Product | D1: Category | E1: Region | F1: Salesperson | G1: Quantity | H1: Unit_Price | I1: Sales_Amount | J1: Customer_Rating | K1: Month | L1: Month_Sort
A2: ORD001 | B2: 46025 | C2: Laptop | D2: Electronics | E2: South | F2: Ade | G2: 2 | H2: 450000 | I2: 900000 | J2: 5 | K2: =TEXT(B2,"mmm yyyy") -> Jan 2026 | L2: =DATE(YEAR(B2),MONTH(B2),1) -> 46023
A3: ORD002 | B3: 46027 | C3: Mouse | D3: Accessories | E3: West | F3: Bola | G3: 10 | H3: 8000 | I3: 80000 | J3: 4 | K3: =TEXT(B3,"mmm yyyy") -> Jan 2026 | L3: =DATE(YEAR(B3),MONTH(B3),1) -> 46023
A4: ORD003 | B4: 46030 | C4: Keyboard | D4: Accessories | E4: North | F4: Chidi | G4: 6 | H4: 15000 | I4: 90000 | J4: 4 | K4: =TEXT(B4,"mmm yyyy") -> Jan 2026 | L4: =DATE(YEAR(B4),MONTH(B4),1) -> 46023
A5: ORD004 | B5: 46034 | C5: Monitor | D5: Electronics | E5: East | F5: Amina | G5: 3 | H5: 120000 | I5: 360000 | J5: 5 | K5: =TEXT(B5,"mmm yyyy") -> Jan 2026 | L5: =DATE(YEAR(B5),MONTH(B5),1) -> 46023
A6: ORD005 | B6: 46037 | C6: Phone | D6: Electronics | E6: South | F6: Tunde | G6: 4 | H6: 250000 | I6: 1000000 | J6: 5 | K6: =TEXT(B6,"mmm yyyy") -> Jan 2026 | L6: =DATE(YEAR(B6),MONTH(B6),1) -> 46023
A7: ORD006 | B7: 46040 | C7: Headset | D7: Accessories | E7: West | F7: Bola | G7: 8 | H7: 20000 | I7: 160000 | J7: 3 | K7: =TEXT(B7,"mmm yyyy") -> Jan 2026 | L7: =DATE(YEAR(B7),MONTH(B7),1) -> 46023
A8: ORD007 | B8: 46042 | C8: Printer | D8: Office Equipment | E8: North | F8: Ade | G8: 2 | H8: 95000 | I8: 190000 | J8: 4 | K8: =TEXT(B8,"mmm yyyy") -> Jan 2026 | L8: =DATE(YEAR(B8),MONTH(B8),1) -> 46023
A9: ORD008 | B9: 46044 | C9: Tablet | D9: Electronics | E9: East | F9: Chidi | G9: 3 | H9: 180000 | I9: 540000 | J9: 5 | K9: =TEXT(B9,"mmm yyyy") -> Jan 2026 | L9: =DATE(YEAR(B9),MONTH(B9),1) -> 46023
A10: ORD009 | B10: 46047 | C10: Mouse | D10: Accessories | E10: South | F10: Amina | G10: 12 | H10: 8000 | I10: 96000 | J10: 4 | K10: =TEXT(B10,"mmm yyyy") -> Jan 2026 | L10: =DATE(YEAR(B10),MONTH(B10),1) -> 46023
A11: ORD010 | B11: 46049 | C11: Laptop | D11: Electronics | E11: West | F11: Tunde | G11: 1 | H11: 450000 | I11: 450000 | J11: 5 | K11: =TEXT(B11,"mmm yyyy") -> Jan 2026 | L11: =DATE(YEAR(B11),MONTH(B11),1) -> 46023
A12: ORD011 | B12: 46055 | C12: Monitor | D12: Electronics | E12: North | F12: Ade | G12: 4 | H12: 120000 | I12: 480000 | J12: 4 | K12: =TEXT(B12,"mmm yyyy") -> Feb 2026 | L12: =DATE(YEAR(B12),MONTH(B12),1) -> 46054
A13: ORD012 | B13: 46057 | C13: Keyboard | D13: Accessories | E13: East | F13: Bola | G13: 7 | H13: 15000 | I13: 105000 | J13: 3 | K13: =TEXT(B13,"mmm yyyy") -> Feb 2026 | L13: =DATE(YEAR(B13),MONTH(B13),1) -> 46054
... A31: ORD030 | B31: 46111 | C31: Tablet | D31: Electronics | E31: West | F31: Tunde | G31: 4 | H31: 180000 | I31: 720000 | J31: 5 | K31: =TEXT(B31,"mmm yyyy") -> Mar 2026 | L31: =DATE(YEAR(B31),MONTH(B31),1) -> 46082

Sheet Dashboard Calc
A1: Metric | B1: Value | D1: Product | E1: Sales | G1: Region | H1: Sales | J1: Salesperson | K1: Sales | M1: Month | N1: Sales | P1: Category | Q1: Sales | S1: Product | T1: Rating
A2: Total Revenue | B2: =SUMPRODUCT(('Retail Sales Data'!$B$2:$B$31>=Dashboard!$B$8)*('Retail Sales Data'!$B$2:$B$31<=Dashboard!$D$8)*IF(Dashboard!$F$8="All",1,--('Retail Sales Data'!$C$2:$C$31=Dashboard!$F$8))*IF(Dashboard!$H$8="All",1,--('Retail Sales Data'!$D$2:$D$31=Dashboard!$H$8))*IF(Dashboard!$J$8="All",1,--('Retail Sales Data'!$E$2:$E$31=Dashboard!$J$8))*IF(Dashboard!$L$8="All",1,--('Retail Sales Data'!$F$2:$F$31=Dashboard!$L$8))*'Retail Sales Data'!$I$2:$I$31) -> 12258000 | D2: Headset | E2: =SUMPRODUCT(('Retail Sales Data'!$B$2:$B$31>=Dashboard!$B$8)*('Retail Sales Data'!$B$2:$B$31<=Dashboard!$D$8)*IF(Dashboard!$F$8="All",1,--('Retail Sales Data'!$C$2:$C$31=Dashboard!$F$8))*IF(Dashboard!$H$8="All",1,--('Retail Sales Data'!$D$2:$D$31=Dashboard!$H$8))*IF(Dashboard!$J$8="All",1,--('Retail Sales Data'!$E$2:$E$31=Dashboard!$J$8))*IF(Dashboard!$L$8="All",1,--('Retail Sales Data'!$F$2:$F$31=Dashboard!$L$8))*--('Retail Sales Data'!$C$2:$C$31=D2)*'Retail Sales Data'!$I$2:$I$31) -> 460000 | G2: East | H2: =SUMPRODUCT(('Retail Sales Data'!$B$2:$B$31>=Dashboard!$B$8)*('Retail Sales Data'!$B$2:$B$31<=Dashboard!$D$8)*IF(Dashboard!$F$8="All",1,--('Retail Sales Data'!$C$2:$C$31=Dashboard!$F$8))*IF(Dashboard!$H$8="All",1,--('Retail Sales Data'!$D$2:$D$31=Dashboard!$H$8))*IF(Dashboard!$J$8="All",1,--('Retail Sales Data'!$E$2:$E$31=Dashboard!$J$8))*IF(Dashboard!$L$8="All",1,--('Retail Sales Data'!$F$2:$F$31=Dashboard!$L$8))*--('Retail Sales Data'!$E$2:$E$31=G2)*'Retail Sales Data'!$I$2:$I$31) -> 2127000 | J2: Ade | K2: =SUMPRODUCT(('Retail Sales Data'!$B$2:$B$31>=Dashboard!$B$8)*('Retail Sales Data'!$B$2:$B$31<=Dashboard!$D$8)*IF(Dashboard!$F$8="All",1,--('Retail Sales Data'!$C$2:$C$31=Dashboard!$F$8))*IF(Dashboard!$H$8="All",1,--('Retail Sales Data'!$D$2:$D$31=Dashboard!$H$8))*IF(Dashboard!$J$8="All",1,--('Retail Sales Data'!$E$2:$E$31=Dashboard!$J$8))*IF(Dashboard!$L$8="All",1,--('Retail Sales Data'!$F$2:$F$31=Dashboard!$L$8))*--('Retail Sales Data'!$F$2:$F$31=J2)*'Retail Sales Data'!$I$2:$I$31) -> 2500000 | M2: 46023 | N2: =SUMPRODUCT(('Retail Sales Data'!$B$2:$B$31>=Dashboard!$B$8)*('Retail Sales Data'!$B$2:$B$31<=Dashboard!$D$8)*IF(Dashboard!$F$8="All",1,--('Retail Sales Data'!$C$2:$C$31=Dashboard!$F$8))*IF(Dashboard!$H$8="All",1,--('Retail Sales Data'!$D$2:$D$31=Dashboard!$H$8))*IF(Dashboard!$J$8="All",1,--('Retail Sales Data'!$E$2:$E$31=Dashboard!$J$8))*IF(Dashboard!$L$8="All",1,--('Retail Sales Data'!$F$2:$F$31=Dashboard!$L$8))*--('Retail Sales Data'!$B$2:$B$31>=M2)*--('Retail Sales Data'!$B$2:$B$31<EDATE(M2,1))*'Retail Sales Data'!$I$2:$I$31) -> 3866000 | P2: Accessories | Q2: =SUMPRODUCT(('Retail Sales Data'!$B$2:$B$31>=Dashboard!$B$8)*('Retail Sales Data'!$B$2:$B$31<=Dashboard!$D$8)*IF(Dashboard!$F$8="All",1,--('Retail Sales Data'!$C$2:$C$31=Dashboard!$F$8))*IF(Dashboard!$H$8="All",1,--('Retail Sales Data'!$D$2:$D$31=Dashboard!$H$8))*IF(Dashboard!$J$8="All",1,--('Retail Sales Data'!$E$2:$E$31=Dashboard!$J$8))*IF(Dashboard!$L$8="All",1,--('Retail Sales Data'!$F$2:$F$31=Dashboard!$L$8))*--('Retail Sales Data'!$D$2:$D$31=P2)*'Retail Sales Data'!$I$2:$I$31) -> 1173000 | S2: Headset | T2: =IFERROR(SUMPRODUCT(('Retail Sales Data'!$B$2:$B$31>=Dashboard!$B$8)*('Retail Sales Data'!$B$2:$B$31<=Dashboard!$D$8)*IF(Dashboard!$F$8="All",1,--('Retail Sales Data'!$C$2:$C$31=Dashboard!$F$8))*IF(Dashboard!$H$8="All",1,--('Retail Sales Data'!$D$2:$D$31=Dashboard!$H$8))*IF(Dashboard!$J$8="All",1,--('Retail Sales Data'!$E$2:$E$31=Dashboard!$J$8))*IF(Dashboard!$L$8="All",1,--('Retail Sales Data'!$F$2:$F$31=Dashboard!$L$8))*--('Retail Sales Data'!$C$2:$C$31=S2)*'Retail Sales Data'!$J$2:$J$31)/SUMPRODUCT(('Retail Sales Data'!$B$2:$B$31>=Dashboard!$B$8)*('Retail Sales Data'!$B$2:$B$31<=Dashboard!$D$8)*IF(Dashboard!$F$8="All",1,--('Retail Sales Data'!$C$2:$C$31=Dashboard!$F$8))*IF(Dashboard!$H$8="All",1,--('Retail Sales Data'!$D$2:$D$31=Dashboard!$H$8))*IF(Dashboard!$J$8="All",1,--('Retail Sales Data'!$E$2:$E$31=Dashboard!$J$8))*IF(Dashboard!$L$8="All",1,--('Retail Sales Data'!$F$2:$F$31=Dashboard!$L$8))*--('Retail Sales Data'!$C$2:$C$31=S2)),0) -> 4
A3: Total Orders | B3: =SUMPRODUCT(('Retail Sales Data'!$B$2:$B$31>=Dashboard!$B$8)*('Retail Sales Data'!$B$2:$B$31<=Dashboard!$D$8)*IF(Dashboard!$F$8="All",1,--('Retail Sales Data'!$C$2:$C$31=Dashboard!$F$8))*IF(Dashboard!$H$8="All",1,--('Retail Sales Data'!$D$2:$D$31=Dashboard!$H$8))*IF(Dashboard!$J$8="All",1,--('Retail Sales Data'!$E$2:$E$31=Dashboard!$J$8))*IF(Dashboard!$L$8="All",1,--('Retail Sales Data'!$F$2:$F$31=Dashboard!$L$8))) -> 30 | D3: Keyboard | E3: =SUMPRODUCT(('Retail Sales Data'!$B$2:$B$31>=Dashboard!$B$8)*('Retail Sales Data'!$B$2:$B$31<=Dashboard!$D$8)*IF(Dashboard!$F$8="All",1,--('Retail Sales Data'!$C$2:$C$31=Dashboard!$F$8))*IF(Dashboard!$H$8="All",1,--('Retail Sales Data'!$D$2:$D$31=Dashboard!$H$8))*IF(Dashboard!$J$8="All",1,--('Retail Sales Data'!$E$2:$E$31=Dashboard!$J$8))*IF(Dashboard!$L$8="All",1,--('Retail Sales Data'!$F$2:$F$31=Dashboard!$L$8))*--('Retail Sales Data'!$C$2:$C$31=D3)*'Retail Sales Data'!$I$2:$I$31) -> 345000 | G3: North | H3: =SUMPRODUCT(('Retail Sales Data'!$B$2:$B$31>=Dashboard!$B$8)*('Retail Sales Data'!$B$2:$B$31<=Dashboard!$D$8)*IF(Dashboard!$F$8="All",1,--('Retail Sales Data'!$C$2:$C$31=Dashboard!$F$8))*IF(Dashboard!$H$8="All",1,--('Retail Sales Data'!$D$2:$D$31=Dashboard!$H$8))*IF(Dashboard!$J$8="All",1,--('Retail Sales Data'!$E$2:$E$31=Dashboard!$J$8))*IF(Dashboard!$L$8="All",1,--('Retail Sales Data'!$F$2:$F$31=Dashboard!$L$8))*--('Retail Sales Data'!$E$2:$E$31=G3)*'Retail Sales Data'!$I$2:$I$31) -> 2400000 | J3: Amina | K3: =SUMPRODUCT(('Retail Sales Data'!$B$2:$B$31>=Dashboard!$B$8)*('Retail Sales Data'!$B$2:$B$31<=Dashboard!$D$8)*IF(Dashboard!$F$8="All",1,--('Retail Sales Data'!$C$2:$C$31=Dashboard!$F$8))*IF(Dashboard!$H$8="All",1,--('Retail Sales Data'!$D$2:$D$31=Dashboard!$H$8))*IF(Dashboard!$J$8="All",1,--('Retail Sales Data'!$E$2:$E$31=Dashboard!$J$8))*IF(Dashboard!$L$8="All",1,--('Retail Sales Data'!$F$2:$F$31=Dashboard!$L$8))*--('Retail Sales Data'!$F$2:$F$31=J3)*'Retail Sales Data'!$I$2:$I$31) -> 1291000 | M3: 46054 | N3: =SUMPRODUCT(('Retail Sales Data'!$B$2:$B$31>=Dashboard!$B$8)*('Retail Sales Data'!$B$2:$B$31<=Dashboard!$D$8)*IF(Dashboard!$F$8="All",1,--('Retail Sales Data'!$C$2:$C$31=Dashboard!$F$8))*IF(Dashboard!$H$8="All",1,--('Retail Sales Data'!$D$2:$D$31=Dashboard!$H$8))*IF(Dashboard!$J$8="All",1,--('Retail Sales Data'!$E$2:$E$31=Dashboard!$J$8))*IF(Dashboard!$L$8="All",1,--('Retail Sales Data'!$F$2:$F$31=Dashboard!$L$8))*--('Retail Sales Data'!$B$2:$B$31>=M3)*--('Retail Sales Data'!$B$2:$B$31<EDATE(M3,1))*'Retail Sales Data'!$I$2:$I$31) -> 4670000 | P3: Electronics | Q3: =SUMPRODUCT(('Retail Sales Data'!$B$2:$B$31>=Dashboard!$B$8)*('Retail Sales Data'!$B$2:$B$31<=Dashboard!$D$8)*IF(Dashboard!$F$8="All",1,--('Retail Sales Data'!$C$2:$C$31=Dashboard!$F$8))*IF(Dashboard!$H$8="All",1,--('Retail Sales Data'!$D$2:$D$31=Dashboard!$H$8))*IF(Dashboard!$J$8="All",1,--('Retail Sales Data'!$E$2:$E$31=Dashboard!$J$8))*IF(Dashboard!$L$8="All",1,--('Retail Sales Data'!$F$2:$F$31=Dashboard!$L$8))*--('Retail Sales Data'!$D$2:$D$31=P3)*'Retail Sales Data'!$I$2:$I$31) -> 10040000 | S3: Keyboard | T3: =IFERROR(SUMPRODUCT(('Retail Sales Data'!$B$2:$B$31>=Dashboard!$B$8)*('Retail Sales Data'!$B$2:$B$31<=Dashboard!$D$8)*IF(Dashboard!$F$8="All",1,--('Retail Sales Data'!$C$2:$C$31=Dashboard!$F$8))*IF(Dashboard!$H$8="All",1,--('Retail Sales Data'!$D$2:$D$31=Dashboard!$H$8))*IF(Dashboard!$J$8="All",1,--('Retail Sales Data'!$E$2:$E$31=Dashboard!$J$8))*IF(Dashboard!$L$8="All",1,--('Retail Sales Data'!$F$2:$F$31=Dashboard!$L$8))*--('Retail Sales Data'!$C$2:$C$31=S3)*'Retail Sales Data'!$J$2:$J$31)/SUMPRODUCT(('Retail Sales Data'!$B$2:$B$31>=Dashboard!$B$8)*('Retail Sales Data'!$B$2:$B$31<=Dashboard!$D$8)*IF(Dashboard!$F$8="All",1,--('Retail Sales Data'!$C$2:$C$31=Dashboard!$F$8))*IF(Dashboard!$H$8="All",1,--('Retail Sales Data'!$D$2:$D$31=Dashboard!$H$8))*IF(Dashboard!$J$8="All",1,--('Retail Sales Data'!$E$2:$E$31=Dashboard!$J$8))*IF(Dashboard!$L$8="All",1,--('Retail Sales Data'!$F$2:$F$31=Dashboard!$L$8))*--('Retail Sales Data'!$C$2:$C$31=S3)),0) -> 3.6666667
A4: Total Quantity | B4: =SUMPRODUCT(('Retail Sales Data'!$B$2:$B$31>=Dashboard!$B$8)*('Retail Sales Data'!$B$2:$B$31<=Dashboard!$D$8)*IF(Dashboard!$F$8="All",1,--('Retail Sales Data'!$C$2:$C$31=Dashboard!$F$8))*IF(Dashboard!$H$8="All",1,--('Retail Sales Data'!$D$2:$D$31=Dashboard!$H$8))*IF(Dashboard!$J$8="All",1,--('Retail Sales Data'!$E$2:$E$31=Dashboard!$J$8))*IF(Dashboard!$L$8="All",1,--('Retail Sales Data'!$F$2:$F$31=Dashboard!$L$8))*'Retail Sales Data'!$G$2:$G$31) -> 149 | D4: Laptop | E4: =SUMPRODUCT(('Retail Sales Data'!$B$2:$B$31>=Dashboard!$B$8)*('Retail Sales Data'!$B$2:$B$31<=Dashboard!$D$8)*IF(Dashboard!$F$8="All",1,--('Retail Sales Data'!$C$2:$C$31=Dashboard!$F$8))*IF(Dashboard!$H$8="All",1,--('Retail Sales Data'!$D$2:$D$31=Dashboard!$H$8))*IF(Dashboard!$J$8="All",1,--('Retail Sales Data'!$E$2:$E$31=Dashboard!$J$8))*IF(Dashboard!$L$8="All",1,--('Retail Sales Data'!$F$2:$F$31=Dashboard!$L$8))*--('Retail Sales Data'!$C$2:$C$31=D4)*'Retail Sales Data'!$I$2:$I$31) -> 2700000 | G4: South | H4: =SUMPRODUCT(('Retail Sales Data'!$B$2:$B$31>=Dashboard!$B$8)*('Retail Sales Data'!$B$2:$B$31<=Dashboard!$D$8)*IF(Dashboard!$F$8="All",1,--('Retail Sales Data'!$C$2:$C$31=Dashboard!$F$8))*IF(Dashboard!$H$8="All",1,--('Retail Sales Data'!$D$2:$D$31=Dashboard!$H$8))*IF(Dashboard!$J$8="All",1,--('Retail Sales Data'!$E$2:$E$31=Dashboard!$J$8))*IF(Dashboard!$L$8="All",1,--('Retail Sales Data'!$F$2:$F$31=Dashboard!$L$8))*--('Retail Sales Data'!$E$2:$E$31=G4)*'Retail Sales Data'!$I$2:$I$31) -> 4936000 | J4: Bola | K4: =SUMPRODUCT(('Retail Sales Data'!$B$2:$B$31>=Dashboard!$B$8)*('Retail Sales Data'!$B$2:$B$31<=Dashboard!$D$8)*IF(Dashboard!$F$8="All",1,--('Retail Sales Data'!$C$2:$C$31=Dashboard!$F$8))*IF(Dashboard!$H$8="All",1,--('Retail Sales Data'!$D$2:$D$31=Dashboard!$H$8))*IF(Dashboard!$J$8="All",1,--('Retail Sales Data'!$E$2:$E$31=Dashboard!$J$8))*IF(Dashboard!$L$8="All",1,--('Retail Sales Data'!$F$2:$F$31=Dashboard!$L$8))*--('Retail Sales Data'!$F$2:$F$31=J4)*'Retail Sales Data'!$I$2:$I$31) -> 2125000 | M4: 46082 | N4: =SUMPRODUCT(('Retail Sales Data'!$B$2:$B$31>=Dashboard!$B$8)*('Retail Sales Data'!$B$2:$B$31<=Dashboard!$D$8)*IF(Dashboard!$F$8="All",1,--('Retail Sales Data'!$C$2:$C$31=Dashboard!$F$8))*IF(Dashboard!$H$8="All",1,--('Retail Sales Data'!$D$2:$D$31=Dashboard!$H$8))*IF(Dashboard!$J$8="All",1,--('Retail Sales Data'!$E$2:$E$31=Dashboard!$J$8))*IF(Dashboard!$L$8="All",1,--('Retail Sales Data'!$F$2:$F$31=Dashboard!$L$8))*--('Retail Sales Data'!$B$2:$B$31>=M4)*--('Retail Sales Data'!$B$2:$B$31<EDATE(M4,1))*'Retail Sales Data'!$I$2:$I$31) -> 3722000 | P4: Office Equipment | Q4: =SUMPRODUCT(('Retail Sales Data'!$B$2:$B$31>=Dashboard!$B$8)*('Retail Sales Data'!$B$2:$B$31<=Dashboard!$D$8)*IF(Dashboard!$F$8="All",1,--('Retail Sales Data'!$C$2:$C$31=Dashboard!$F$8))*IF(Dashboard!$H$8="All",1,--('Retail Sales Data'!$D$2:$D$31=Dashboard!$H$8))*IF(Dashboard!$J$8="All",1,--('Retail Sales Data'!$E$2:$E$31=Dashboard!$J$8))*IF(Dashboard!$L$8="All",1,--('Retail Sales Data'!$F$2:$F$31=Dashboard!$L$8))*--('Retail Sales Data'!$D$2:$D$31=P4)*'Retail Sales Data'!$I$2:$I$31) -> 1045000 | S4: Laptop | T4: =IFERROR(SUMPRODUCT(('Retail Sales Data'!$B$2:$B$31>=Dashboard!$B$8)*('Retail Sales Data'!$B$2:$B$31<=Dashboard!$D$8)*IF(Dashboard!$F$8="All",1,--('Retail Sales Data'!$C$2:$C$31=Dashboard!$F$8))*IF(Dashboard!$H$8="All",1,--('Retail Sales Data'!$D$2:$D$31=Dashboard!$H$8))*IF(Dashboard!$J$8="All",1,--('Retail Sales Data'!$E$2:$E$31=Dashboard!$J$8))*IF(Dashboard!$L$8="All",1,--('Retail Sales Data'!$F$2:$F$31=Dashboard!$L$8))*--('Retail Sales Data'!$C$2:$C$31=S4)*'Retail Sales Data'!$J$2:$J$31)/SUMPRODUCT(('Retail Sales Data'!$B$2:$B$31>=Dashboard!$B$8)*('Retail Sales Data'!$B$2:$B$31<=Dashboard!$D$8)*IF(Dashboard!$F$8="All",1,--('Retail Sales Data'!$C$2:$C$31=Dashboard!$F$8))*IF(Dashboard!$H$8="All",1,--('Retail Sales Data'!$D$2:$D$31=Dashboard!$H$8))*IF(Dashboard!$J$8="All",1,--('Retail Sales Data'!$E$2:$E$31=Dashboard!$J$8))*IF(Dashboard!$L$8="All",1,--('Retail Sales Data'!$F$2:$F$31=Dashboard!$L$8))*--('Retail Sales Data'!$C$2:$C$31=S4)),0) -> 5
A5: Average Order Value | B5: =IFERROR(B2/B3,0) -> 408600 | D5: Monitor | E5: =SUMPRODUCT(('Retail Sales Data'!$B$2:$B$31>=Dashboard!$B$8)*('Retail Sales Data'!$B$2:$B$31<=Dashboard!$D$8)*IF(Dashboard!$F$8="All",1,--('Retail Sales Data'!$C$2:$C$31=Dashboard!$F$8))*IF(Dashboard!$H$8="All",1,--('Retail Sales Data'!$D$2:$D$31=Dashboard!$H$8))*IF(Dashboard!$J$8="All",1,--('Retail Sales Data'!$E$2:$E$31=Dashboard!$J$8))*IF(Dashboard!$L$8="All",1,--('Retail Sales Data'!$F$2:$F$31=Dashboard!$L$8))*--('Retail Sales Data'!$C$2:$C$31=D5)*'Retail Sales Data'!$I$2:$I$31) -> 1680000 | G5: West | H5: =SUMPRODUCT(('Retail Sales Data'!$B$2:$B$31>=Dashboard!$B$8)*('Retail Sales Data'!$B$2:$B$31<=Dashboard!$D$8)*IF(Dashboard!$F$8="All",1,--('Retail Sales Data'!$C$2:$C$31=Dashboard!$F$8))*IF(Dashboard!$H$8="All",1,--('Retail Sales Data'!$D$2:$D$31=Dashboard!$H$8))*IF(Dashboard!$J$8="All",1,--('Retail Sales Data'!$E$2:$E$31=Dashboard!$J$8))*IF(Dashboard!$L$8="All",1,--('Retail Sales Data'!$F$2:$F$31=Dashboard!$L$8))*--('Retail Sales Data'!$E$2:$E$31=G5)*'Retail Sales Data'!$I$2:$I$31) -> 2795000 | J5: Chidi | K5: =SUMPRODUCT(('Retail Sales Data'!$B$2:$B$31>=Dashboard!$B$8)*('Retail Sales Data'!$B$2:$B$31<=Dashboard!$D$8)*IF(Dashboard!$F$8="All",1,--('Retail Sales Data'!$C$2:$C$31=Dashboard!$F$8))*IF(Dashboard!$H$8="All",1,--('Retail Sales Data'!$D$2:$D$31=Dashboard!$H$8))*IF(Dashboard!$J$8="All",1,--('Retail Sales Data'!$E$2:$E$31=Dashboard!$J$8))*IF(Dashboard!$L$8="All",1,--('Retail Sales Data'!$F$2:$F$31=Dashboard!$L$8))*--('Retail Sales Data'!$F$2:$F$31=J5)*'Retail Sales Data'!$I$2:$I$31) -> 2612000 | S5: Monitor | T5: =IFERROR(SUMPRODUCT(('Retail Sales Data'!$B$2:$B$31>=Dashboard!$B$8)*('Retail Sales Data'!$B$2:$B$31<=Dashboard!$D$8)*IF(Dashboard!$F$8="All",1,--('Retail Sales Data'!$C$2:$C$31=Dashboard!$F$8))*IF(Dashboard!$H$8="All",1,--('Retail Sales Data'!$D$2:$D$31=Dashboard!$H$8))*IF(Dashboard!$J$8="All",1,--('Retail Sales Data'!$E$2:$E$31=Dashboard!$J$8))*IF(Dashboard!$L$8="All",1,--('Retail Sales Data'!$F$2:$F$31=Dashboard!$L$8))*--('Retail Sales Data'!$C$2:$C$31=S5)*'Retail Sales Data'!$J$2:$J$31)/SUMPRODUCT(('Retail Sales Data'!$B$2:$B$31>=Dashboard!$B$8)*('Retail Sales Data'!$B$2:$B$31<=Dashboard!$D$8)*IF(Dashboard!$F$8="All",1,--('Retail Sales Data'!$C$2:$C$31=Dashboard!$F$8))*IF(Dashboard!$H$8="All",1,--('Retail Sales Data'!$D$2:$D$31=Dashboard!$H$8))*IF(Dashboard!$J$8="All",1,--('Retail Sales Data'!$E$2:$E$31=Dashboard!$J$8))*IF(Dashboard!$L$8="All",1,--('Retail Sales Data'!$F$2:$F$31=Dashboard!$L$8))*--('Retail Sales Data'!$C$2:$C$31=S5)),0) -> 4
A6: Average Customer Rating | B6: =IFERROR(SUMPRODUCT(('Retail Sales Data'!$B$2:$B$31>=Dashboard!$B$8)*('Retail Sales Data'!$B$2:$B$31<=Dashboard!$D$8)*IF(Dashboard!$F$8="All",1,--('Retail Sales Data'!$C$2:$C$31=Dashboard!$F$8))*IF(Dashboard!$H$8="All",1,--('Retail Sales Data'!$D$2:$D$31=Dashboard!$H$8))*IF(Dashboard!$J$8="All",1,--('Retail Sales Data'!$E$2:$E$31=Dashboard!$J$8))*IF(Dashboard!$L$8="All",1,--('Retail Sales Data'!$F$2:$F$31=Dashboard!$L$8))*'Retail Sales Data'!$J$2:$J$31)/B3,0) -> 4.3 | D6: Mouse | E6: =SUMPRODUCT(('Retail Sales Data'!$B$2:$B$31>=Dashboard!$B$8)*('Retail Sales Data'!$B$2:$B$31<=Dashboard!$D$8)*IF(Dashboard!$F$8="All",1,--('Retail Sales Data'!$C$2:$C$31=Dashboard!$F$8))*IF(Dashboard!$H$8="All",1,--('Retail Sales Data'!$D$2:$D$31=Dashboard!$H$8))*IF(Dashboard!$J$8="All",1,--('Retail Sales Data'!$E$2:$E$31=Dashboard!$J$8))*IF(Dashboard!$L$8="All",1,--('Retail Sales Data'!$F$2:$F$31=Dashboard!$L$8))*--('Retail Sales Data'!$C$2:$C$31=D6)*'Retail Sales Data'!$I$2:$I$31) -> 368000 | J6: Tunde | K6: =SUMPRODUCT(('Retail Sales Data'!$B$2:$B$31>=Dashboard!$B$8)*('Retail Sales Data'!$B$2:$B$31<=Dashboard!$D$8)*IF(Dashboard!$F$8="All",1,--('Retail Sales Data'!$C$2:$C$31=Dashboard!$F$8))*IF(Dashboard!$H$8="All",1,--('Retail Sales Data'!$D$2:$D$31=Dashboard!$H$8))*IF(Dashboard!$J$8="All",1,--('Retail Sales Data'!$E$2:$E$31=Dashboard!$J$8))*IF(Dashboard!$L$8="All",1,--('Retail Sales Data'!$F$2:$F$31=Dashboard!$L$8))*--('Retail Sales Data'!$F$2:$F$31=J6)*'Retail Sales Data'!$I$2:$I$31) -> 3730000 | S6: Mouse | T6: =IFERROR(SUMPRODUCT(('Retail Sales Data'!$B$2:$B$31>=Dashboard!$B$8)*('Retail Sales Data'!$B$2:$B$31<=Dashboard!$D$8)*IF(Dashboard!$F$8="All",1,--('Retail Sales Data'!$C$2:$C$31=Dashboard!$F$8))*IF(Dashboard!$H$8="All",1,--('Retail Sales Data'!$D$2:$D$31=Dashboard!$H$8))*IF(Dashboard!$J$8="All",1,--('Retail Sales Data'!$E$2:$E$31=Dashboard!$J$8))*IF(Dashboard!$L$8="All",1,--('Retail Sales Data'!$F$2:$F$31=Dashboard!$L$8))*--('Retail Sales Data'!$C$2:$C$31=S6)*'Retail Sales Data'!$J$2:$J$31)/SUMPRODUCT(('Retail Sales Data'!$B$2:$B$31>=Dashboard!$B$8)*('Retail Sales Data'!$B$2:$B$31<=Dashboard!$D$8)*IF(Dashboard!$F$8="All",1,--('Retail Sales Data'!$C$2:$C$31=Dashboard!$F$8))*IF(Dashboard!$H$8="All",1,--('Retail Sales Data'!$D$2:$D$31=Dashboard!$H$8))*IF(Dashboard!$J$8="All",1,--('Retail Sales Data'!$E$2:$E$31=Dashboard!$J$8))*IF(Dashboard!$L$8="All",1,--('Retail Sales Data'!$F$2:$F$31=Dashboard!$L$8))*--('Retail Sales Data'!$C$2:$C$31=S6)),0) -> 3.75
A7: Top Product | B7: =INDEX(D2:D9,MATCH(MAX(E2:E9),E2:E9,0)) -> Phone | D7: Phone | E7: =SUMPRODUCT(('Retail Sales Data'!$B$2:$B$31>=Dashboard!$B$8)*('Retail Sales Data'!$B$2:$B$31<=Dashboard!$D$8)*IF(Dashboard!$F$8="All",1,--('Retail Sales Data'!$C$2:$C$31=Dashboard!$F$8))*IF(Dashboard!$H$8="All",1,--('Retail Sales Data'!$D$2:$D$31=Dashboard!$H$8))*IF(Dashboard!$J$8="All",1,--('Retail Sales Data'!$E$2:$E$31=Dashboard!$J$8))*IF(Dashboard!$L$8="All",1,--('Retail Sales Data'!$F$2:$F$31=Dashboard!$L$8))*--('Retail Sales Data'!$C$2:$C$31=D7)*'Retail Sales Data'!$I$2:$I$31) -> 3500000 | S7: Phone | T7: =IFERROR(SUMPRODUCT(('Retail Sales Data'!$B$2:$B$31>=Dashboard!$B$8)*('Retail Sales Data'!$B$2:$B$31<=Dashboard!$D$8)*IF(Dashboard!$F$8="All",1,--('Retail Sales Data'!$C$2:$C$31=Dashboard!$F$8))*IF(Dashboard!$H$8="All",1,--('Retail Sales Data'!$D$2:$D$31=Dashboard!$H$8))*IF(Dashboard!$J$8="All",1,--('Retail Sales Data'!$E$2:$E$31=Dashboard!$J$8))*IF(Dashboard!$L$8="All",1,--('Retail Sales Data'!$F$2:$F$31=Dashboard!$L$8))*--('Retail Sales Data'!$C$2:$C$31=S7)*'Retail Sales Data'!$J$2:$J$31)/SUMPRODUCT(('Retail Sales Data'!$B$2:$B$31>=Dashboard!$B$8)*('Retail Sales Data'!$B$2:$B$31<=Dashboard!$D$8)*IF(Dashboard!$F$8="All",1,--('Retail Sales Data'!$C$2:$C$31=Dashboard!$F$8))*IF(Dashboard!$H$8="All",1,--('Retail Sales Data'!$D$2:$D$31=Dashboard!$H$8))*IF(Dashboard!$J$8="All",1,--('Retail Sales Data'!$E$2:$E$31=Dashboard!$J$8))*IF(Dashboard!$L$8="All",1,--('Retail Sales Data'!$F$2:$F$31=Dashboard!$L$8))*--('Retail Sales Data'!$C$2:$C$31=S7)),0) -> 5
A8: Top Region | B8: =INDEX(G2:G5,MATCH(MAX(H2:H5),H2:H5,0)) -> South | D8: Printer | E8: =SUMPRODUCT(('Retail Sales Data'!$B$2:$B$31>=Dashboard!$B$8)*('Retail Sales Data'!$B$2:$B$31<=Dashboard!$D$8)*IF(Dashboard!$F$8="All",1,--('Retail Sales Data'!$C$2:$C$31=Dashboard!$F$8))*IF(Dashboard!$H$8="All",1,--('Retail Sales Data'!$D$2:$D$31=Dashboard!$H$8))*IF(Dashboard!$J$8="All",1,--('Retail Sales Data'!$E$2:$E$31=Dashboard!$J$8))*IF(Dashboard!$L$8="All",1,--('Retail Sales Data'!$F$2:$F$31=Dashboard!$L$8))*--('Retail Sales Data'!$C$2:$C$31=D8)*'Retail Sales Data'!$I$2:$I$31) -> 1045000 | S8: Printer | T8: =IFERROR(SUMPRODUCT(('Retail Sales Data'!$B$2:$B$31>=Dashboard!$B$8)*('Retail Sales Data'!$B$2:$B$31<=Dashboard!$D$8)*IF(Dashboard!$F$8="All",1,--('Retail Sales Data'!$C$2:$C$31=Dashboard!$F$8))*IF(Dashboard!$H$8="All",1,--('Retail Sales Data'!$D$2:$D$31=Dashboard!$H$8))*IF(Dashboard!$J$8="All",1,--('Retail Sales Data'!$E$2:$E$31=Dashboard!$J$8))*IF(Dashboard!$L$8="All",1,--('Retail Sales Data'!$F$2:$F$31=Dashboard!$L$8))*--('Retail Sales Data'!$C$2:$C$31=S8)*'Retail Sales Data'!$J$2:$J$31)/SUMPRODUCT(('Retail Sales Data'!$B$2:$B$31>=Dashboard!$B$8)*('Retail Sales Data'!$B$2:$B$31<=Dashboard!$D$8)*IF(Dashboard!$F$8="All",1,--('Retail Sales Data'!$C$2:$C$31=Dashboard!$F$8))*IF(Dashboard!$H$8="All",1,--('Retail Sales Data'!$D$2:$D$31=Dashboard!$H$8))*IF(Dashboard!$J$8="All",1,--('Retail Sales Data'!$E$2:$E$31=Dashboard!$J$8))*IF(Dashboard!$L$8="All",1,--('Retail Sales Data'!$F$2:$F$31=Dashboard!$L$8))*--('Retail Sales Data'!$C$2:$C$31=S8)),0) -> 4.25
A9: Top Salesperson | B9: =INDEX(J2:J6,MATCH(MAX(K2:K6),K2:K6,0)) -> Tunde | D9: Tablet | E9: =SUMPRODUCT(('Retail Sales Data'!$B$2:$B$31>=Dashboard!$B$8)*('Retail Sales Data'!$B$2:$B$31<=Dashboard!$D$8)*IF(Dashboard!$F$8="All",1,--('Retail Sales Data'!$C$2:$C$31=Dashboard!$F$8))*IF(Dashboard!$H$8="All",1,--('Retail Sales Data'!$D$2:$D$31=Dashboard!$H$8))*IF(Dashboard!$J$8="All",1,--('Retail Sales Data'!$E$2:$E$31=Dashboard!$J$8))*IF(Dashboard!$L$8="All",1,--('Retail Sales Data'!$F$2:$F$31=Dashboard!$L$8))*--('Retail Sales Data'!$C$2:$C$31=D9)*'Retail Sales Data'!$I$2:$I$31) -> 2160000 | S9: Tablet | T9: =IFERROR(SUMPRODUCT(('Retail Sales Data'!$B$2:$B$31>=Dashboard!$B$8)*('Retail Sales Data'!$B$2:$B$31<=Dashboard!$D$8)*IF(Dashboard!$F$8="All",1,--('Retail Sales Data'!$C$2:$C$31=Dashboard!$F$8))*IF(Dashboard!$H$8="All",1,--('Retail Sales Data'!$D$2:$D$31=Dashboard!$H$8))*IF(Dashboard!$J$8="All",1,--('Retail Sales Data'!$E$2:$E$31=Dashboard!$J$8))*IF(Dashboard!$L$8="All",1,--('Retail Sales Data'!$F$2:$F$31=Dashboard!$L$8))*--('Retail Sales Data'!$C$2:$C$31=S9)*'Retail Sales Data'!$J$2:$J$31)/SUMPRODUCT(('Retail Sales Data'!$B$2:$B$31>=Dashboard!$B$8)*('Retail Sales Data'!$B$2:$B$31<=Dashboard!$D$8)*IF(Dashboard!$F$8="All",1,--('Retail Sales Data'!$C$2:$C$31=Dashboard!$F$8))*IF(Dashboard!$H$8="All",1,--('Retail Sales Data'!$D$2:$D$31=Dashboard!$H$8))*IF(Dashboard!$J$8="All",1,--('Retail Sales Data'!$E$2:$E$31=Dashboard!$J$8))*IF(Dashboard!$L$8="All",1,--('Retail Sales Data'!$F$2:$F$31=Dashboard!$L$8))*--('Retail Sales Data'!$C$2:$C$31=S9)),0) -> 4.5

Sheet Lists
A1: Products | B1: Categories | C1: Regions | D1: Salespeople | E1: Dates
A2: All | B2: All | C2: All | D2: All | E2: 46025
A3: Headset | B3: Accessories | C3: East | D3: Ade | E3: 46027
A4: Keyboard | B4: Electronics | C4: North | D4: Amina | E4: 46030
A5: Laptop | B5: Office Equipment | C5: South | D5: Bola | E5: 46034
A6: Monitor | C6: West | D6: Chidi | E6: 46037
A7: Mouse | D7: Tunde | E7: 46040
A8: Phone | E8: 46042
A9: Printer | E9: 46044
A10: Tablet | E10: 46047
E11: 46049
E12: 46055
E13: 46057
E14: 46060
E15: 46063
E16: 46066
E17: 46069
E18: 46073
E19: 46076
E20: 46078
E21: 46081
E22: 46084
... E31: 46111
